{
    "producer": "PDF/UA Composer from T-Base, an Allyant Company, CMD v3.2.0 Engine 57166",
    "creator": "Microsoft\u00ae Word for Microsoft 365",
    "creationdate": "2023-03-01T15:42:10-05:00",
    "author": "TD",
    "moddate": "2023-03-06T13:09:00-05:00",
    "subject": "TD Bank Group Reports First Quarter 2023 Results",
    "title": "TD Bank Group Reports First Quarter 2023 Results",
    "source": "data\\2023_q1_report.pdf",
    "total_pages": "75",
    "page": "0",
    "page_label": "1"
}